fabricease/__init__.py
fabricease/auth.py
fabricease/connection.py
fabricease/database.py
fabricease/exceptions.py
fabricease/utils.py
fabricease-0.1.0.dist-info/licenses/LICENSE
fabricease-0.1.0.dist-info/METADATA
fabricease-0.1.0.dist-info/WHEEL
fabricease-0.1.0.dist-info/entry_points.txt
fabricease-0.1.0.dist-info/top_level.txt
fabricease-0.1.0.dist-info/RECORD
