Metadata-Version: 2.4
Name: fabricease
Version: 0.1.0
Summary: A Simple Python Library for Microsoft Fabric SQL Database Connections
Home-page: https://github.com/Ramseyxlil/fabrisqldb_python_library
Author: Abdulrafiu Izuafa
Author-email: Abdulrafiu Izuafa <abdulrafiu@azurelearnai.org>
License: MIT
Project-URL: Homepage, https://github.com/Ramseyxlil/fabrisqldb_python_library
Project-URL: Repository, https://github.com/Ramseyxlil/fabrisqldb_python_library.git
Project-URL: Issues, https://github.com/Ramseyxlil/fabrisqldb_python_library/issues
Project-URL: Documentation, https://github.com/Ramseyxlil/fabrisqldb_python_library#readme
Project-URL: Changelog, https://github.com/Ramseyxlil/fabrisqldb_python_library/releases
Keywords: microsoft-fabric,sql-database,azure,authentication,pyodbc,database
Platform: any
Classifier: Development Status :: 3 - Alpha
Classifier: Intended Audience :: Developers
Classifier: License :: OSI Approved :: MIT License
Classifier: Operating System :: OS Independent
Classifier: Programming Language :: Python :: 3
Classifier: Programming Language :: Python :: 3.8
Classifier: Programming Language :: Python :: 3.9
Classifier: Programming Language :: Python :: 3.10
Classifier: Programming Language :: Python :: 3.11
Classifier: Programming Language :: Python :: 3.12
Classifier: Topic :: Database
Classifier: Topic :: Software Development :: Libraries :: Python Modules
Classifier: Topic :: Internet :: WWW/HTTP :: Dynamic Content
Classifier: Environment :: Console
Classifier: Framework :: Jupyter
Requires-Python: >=3.8
License-File: LICENSE
Requires-Dist: pyodbc>=4.0.34
Requires-Dist: azure-identity>=1.12.0
Requires-Dist: python-dotenv>=0.19.0
Provides-Extra: dev
Requires-Dist: pytest>=6.0; extra == "dev"
Requires-Dist: pytest-cov>=2.0; extra == "dev"
Requires-Dist: black>=21.0; extra == "dev"
Requires-Dist: flake8>=3.8; extra == "dev"
Requires-Dist: mypy>=0.812; extra == "dev"
Requires-Dist: build>=0.7.0; extra == "dev"
Requires-Dist: twine>=4.0.0; extra == "dev"
Provides-Extra: test
Requires-Dist: pytest>=6.0; extra == "test"
Requires-Dist: pytest-cov>=2.0; extra == "test"
Requires-Dist: pytest-mock>=3.6.0; extra == "test"
Dynamic: author
Dynamic: home-page
Dynamic: license-file
Dynamic: platform
Dynamic: requires-python
